{
  "Tasks": [
    "00 * * * * * * TestClient2 {\"Type\": \"Raw\", \"Request\": \"00 00 06 03 ff ff\", \"Timeout\": 1000}",
    "05 * * * * * * TestClient2 {\"Type\": \"Raw\", \"Request\": \"00 00 06 03 ff ff\", \"Timeout\": 1000}",
    "10 * * * * * * TestClient2 {\"Type\": \"Raw\", \"Request\": \"00 00 06 03 ff ff\", \"Timeout\": 1000}",
    "15 * * * * * * TestClient2 {\"Type\": \"Raw\", \"Request\": \"00 00 06 03 ff ff\", \"Timeout\": 1000}",
    "20 * * * * * * TestClient2 {\"Type\": \"Raw\", \"Request\": \"00 00 06 03 ff ff\", \"Timeout\": 1000}",
    "25 * * * * * * TestClient2 {\"Type\": \"Raw\", \"Request\": \"00 00 06 03 ff ff\", \"Timeout\": 1000}",
    "30 * * * * * * TestClient2 {\"Type\": \"Raw\", \"Request\": \"00 00 06 03 ff ff\", \"Timeout\": 1000}",
    "35 * * * * * * TestClient2 {\"Type\": \"Raw\", \"Request\": \"00 00 06 03 ff ff\", \"Timeout\": 1000}",
    "40 * * * * * * TestClient2 {\"Type\": \"Raw\", \"Request\": \"00 00 06 03 ff ff\", \"Timeout\": 1000}",
    "45 * * * * * * TestClient2 {\"Type\": \"Raw\", \"Request\": \"00 00 06 03 ff ff\", \"Timeout\": 1000}",
    "50 * * * * * * TestClient2 {\"Type\": \"Raw\", \"Request\": \"00 00 06 03 ff ff\", \"Timeout\": 1000}",
    "55 * * * * * * TestClient2 {\"Type\": \"Raw\", \"Request\": \"00 00 06 03 ff ff\", \"Timeout\": 1000}"
  ]
}
